{"weiter":"keine-weitere-seite","echo":"<div class=slide id=158 right=159 left=157 up=155 down=noway><table><tr><td colspan=2><h1>Skiopening\r\n<\/h1><\/td><\/tr><tr><td class='emerged'>\r\n<video style='height: 200px; width: 355px;'  controls onclick='if(\/Android\/.test(navigator.userAgent))this.play();'>\r\n<source src='.\/special\/skiopening.mp4' type='video\/mp4' \/>\r\n<source src='.\/special\/skiopening.webm' type='video\/webm' \/>\r\n<source src='.\/special\/skiopening.ogv' type='video\/ogg' \/><\/video>\r\n<p>Abfahren und feiern: Mitte Dezember er&ouml;ffnet Bayern 1 allj&auml;hrlich die Skisaison mit dem Bayern 1-Skiopening, bei dem alle Wintersportfans den ersten Schnee der Wintersaison genie&szlig;en k&ouml;nnen. Auf und neben der Piste gibt es ein abwechslungsreiches Showprogramm mit fetziger Musik - moderiert von Tilmann Sch&ouml;berl und Thomas Ohrner. F&uuml;r die richtige Apr&egrave;s-Ski-Stimmung am Abend sorgt ein umfangreiches Musikprogramm.<\/p><\/td><\/tr><\/table><\/div>","breadcrumbs":"<span onClick=\"slideto(155)\" class=slideto href=# slideto=155>Events\r\n<\/span> > <span class=slideto href=# slideto=158>Skiopening\r\n<\/span>","right":159,"left":157,"up":155,"down":"noway","headline":"Events","debug":"158"}