{"weiter":"keine-weitere-seite","echo":"<div class=slide id=81 right=noway left=80 up=79 down=noway><table><tr><td colspan=2><h1>Bruttokontaktsummen\/TKPs Sa\r\n<\/h1><\/td><\/tr><tr><td class='emerged'><\/td><\/tr><\/table><\/div>","breadcrumbs":"<span onClick=\"slideto(73)\" class=slideto href=# slideto=73>Young & City\r\n<\/span> > <span onClick=\"slideto(79)\" class=slideto href=# slideto=79>Key Facts E45-69\r\n<\/span> > <span onClick=\"slideto(79)\" class=slideto slideto=79>Key Facts E45-69\r\n<\/span> > <span class=slideto href=# slideto=81>Bruttokontaktsummen\/TKPs Sa\r\n<\/span>","right":"noway","left":80,"up":79,"down":"noway","headline":"Key Facts E45-69","debug":"81"}